cmyui/__init__.py
cmyui/logging.py
cmyui/mysql.py
cmyui/postgres.py
cmyui/utils.py
cmyui/version.py
cmyui/web.py
cmyui/discord/__init__.py
cmyui/discord/webhook.py
cmyui/osu/__init__.py
cmyui/osu/api.py
cmyui/osu/beatmap.py
cmyui/osu/mods.py
cmyui/osu/replay.py
cmyui-1.6.5.dist-info/LICENSE
cmyui-1.6.5.dist-info/METADATA
cmyui-1.6.5.dist-info/WHEEL
cmyui-1.6.5.dist-info/top_level.txt
cmyui-1.6.5.dist-info/RECORD
