Metadata-Version: 2.1
Name: cmyui
Version: 1.6.5
Summary: Tools I find myself constantly rebuilding and reusing.
Home-page: https://github.com/cmyui/cmyui_pkg
Author: cmyui
License: MIT
Platform: UNKNOWN
Classifier: Programming Language :: Python :: 3.9
Classifier: License :: OSI Approved :: MIT License
Requires-Python: >=3.9
